pythonanywhere_wrapper/__init__.py
pythonanywhere_wrapper/client.py
pythonanywhere_wrapper.egg-info/PKG-INFO
pythonanywhere_wrapper.egg-info/SOURCES.txt
pythonanywhere_wrapper.egg-info/dependency_links.txt
pythonanywhere_wrapper.egg-info/requires.txt
pythonanywhere_wrapper.egg-info/top_level.txt
pythonanywhere_wrapper-0.3.1.dist-info/LICENSE
pythonanywhere_wrapper-0.3.1.dist-info/METADATA
pythonanywhere_wrapper-0.3.1.dist-info/WHEEL
pythonanywhere_wrapper-0.3.1.dist-info/top_level.txt
pythonanywhere_wrapper-0.3.1.dist-info/RECORD
