Metadata-Version: 2.1
Name: pythonanywhere-wrapper
Version: 0.3.1
Summary: PythonAnywhere API wrapper.
Home-page: https://github.com/cfc603/pythonanywhere-wrapper
Author: Trevor Watson
Author-email: wtrevor162@gmail.com
License: MIT
Keywords: pythonanywhere pythonanywhere-wrapper pythonanywhere_wrapper
Platform: UNKNOWN
Classifier: Intended Audience :: Developers
Classifier: Topic :: Utilities
Classifier: License :: OSI Approved :: MIT License
Classifier: Natural Language :: English
Classifier: Operating System :: OS Independent
Classifier: Programming Language :: Python :: 3
Classifier: Programming Language :: Python :: 3 :: Only
Classifier: Programming Language :: Python :: 3.6
Classifier: Programming Language :: Python :: 3.7
Classifier: Programming Language :: Python :: 3.8
Classifier: Programming Language :: Python :: 3.9
Classifier: Topic :: Software Development :: Libraries :: Python Modules
Requires-Dist: requests
Requires-Dist: simplejson
Provides-Extra: test
Requires-Dist: coverage ; extra == 'test'
Requires-Dist: flake8 ; extra == 'test'
Requires-Dist: pytest ; extra == 'test'
Requires-Dist: pytest-cov ; extra == 'test'
Requires-Dist: responses ; extra == 'test'
Requires-Dist: tox ; extra == 'test'
